{"_default": {"1": {"Id": "IPQ3E74G", "Date": "28/05/2022", "Time": "12:00", "League": "ARMENIA - VBET PREMIER LEAGUE", "Home": "Ararat Yerevan", "Away": "Ararat-Armenia", "Round": "ROUND 36", "Season": "2021/2022", "Goals_H_HT": 0, "Goals_A_HT": 1, "Goals_H_FT": 0, "Goals_A_FT": 1, "Odd_H": 3.85, "Odd_D": 3.4, "Odd_A": 1.83, "Odd_Over05_HT": 1.44, "Odd_Under05_HT": 2.62, "Odd_Over05_FT": 1.03, "Odd_Under05_FT": 9.2, "Odd_Over15_FT": 1.3, "Odd_Under15_FT": 3.15, "Odd_Over25_FT": 1.87, "Odd_Under25_FT": 1.75, "Odd_BTTS_Yes": 1.8, "Odd_BTTS_No": 1.96, "Odd_1X": 1.91, "Odd_12": 1.27, "Odd_X2": 1.22, "Odd_AH_Neg15_H": 8.6, "Odd_AH_Neg15_A": 1.03, "Odd_AH_Neg10_H": 7.7, "Odd_AH_Neg10_A": 1.05, "Odd_AH_00_H": 2.85, "Odd_AH_00_A": 1.38, "Odd_AH_Pos10_H": 1.48, "Odd_AH_Pos10_A": 2.74, "Odd_AH_Pos15_H": 1.29, "Odd_AH_Pos15_A": 3.42, "Odd_CS_1-0": 10.0, "Odd_CS_2-0": 18.0, "Odd_CS_2-1": 11.0, "Odd_CS_3-0": 51.0, "Odd_CS_3-1": 31.0, "Odd_CS_3-2": 34.0, "Odd_CS_0-0": 8.0, "Odd_CS_1-1": 5.5, "Odd_CS_2-2": 11.0, "Odd_CS_3-3": 61.0, "Odd_CS_4-4": 201.0, "Odd_CS_0-1": 6.0, "Odd_CS_0-2": 7.0, "Odd_CS_1-2": 6.5, "Odd_CS_0-3": 12.0, "Odd_CS_1-3": 11.0, "Odd_CS_2-3": 21.0, "Goals_Minutes_Home": [], "Goals_Minutes_Away": [38]}}}